spectrum_utils/__init__.py
spectrum_utils/fragment_annotation.py
spectrum_utils/iplot.py
spectrum_utils/monosaccharide.lark
spectrum_utils/plot.py
spectrum_utils/proforma.ebnf
spectrum_utils/proforma.py
spectrum_utils/spectrum.py
spectrum_utils/utils.py
tests/__init__.py
tests/fragment_annotation_test.py
tests/proforma_test.py
tests/spectrum_test.py
spectrum_utils-0.4.2.dist-info/LICENSE.txt
spectrum_utils-0.4.2.dist-info/METADATA
spectrum_utils-0.4.2.dist-info/WHEEL
spectrum_utils-0.4.2.dist-info/top_level.txt
spectrum_utils-0.4.2.dist-info/RECORD
