Metadata-Version: 2.1
Name: spectrum-utils
Version: 0.4.2
Summary: Mass spectrometry utility functions
Home-page: https://github.com/bittremieux/spectrum_utils
Author: Wout Bittremieux
Author-email: wbittremieux@health.ucsd.edu
License: Apache 2.0
Project-URL: Documentation, https://spectrum-utils.readthedocs.io/
Project-URL: Bug Tracker, https://github.com/bittremieux/spectrum_utils/issues
Classifier: Intended Audience :: Science/Research
Classifier: License :: OSI Approved :: Apache Software License
Classifier: Operating System :: MacOS
Classifier: Operating System :: Microsoft :: Windows
Classifier: Operating System :: Unix
Classifier: Programming Language :: Python :: 3
Classifier: Topic :: Scientific/Engineering :: Bio-Informatics
Requires-Python: >=3.8
License-File: LICENSE.txt
Requires-Dist: appdirs
Requires-Dist: fastobo
Requires-Dist: lark (>=1.0)
Requires-Dist: matplotlib (>=3.5)
Requires-Dist: numba (>=0.47)
Requires-Dist: numpy
Requires-Dist: pyteomics (>=4.5)
Provides-Extra: dev
Requires-Dist: black ; extra == 'dev'
Requires-Dist: pytest ; extra == 'dev'
Requires-Dist: pytest-cov ; extra == 'dev'
Provides-Extra: docs
Requires-Dist: myst-parser ; extra == 'docs'
Requires-Dist: numpydoc (>=1.1.0) ; extra == 'docs'
Requires-Dist: sphinx (>=3.5.3) ; extra == 'docs'
Requires-Dist: sphinx-rtd-theme (>=0.5.1) ; extra == 'docs'
Requires-Dist: sphinx-markdown-tables ; extra == 'docs'
Provides-Extra: iplot
Requires-Dist: altair ; extra == 'iplot'
Requires-Dist: pandas ; extra == 'iplot'
